{
    "guitar_key": "Bb minor",
    "beat": "4/4",
    "title": "Langin Mage Oba  – ළඟින් මගේ ඔබ",
    "views": 760,
    "Artist": " Chandralekha Perera",
    "Lyrics": " Nandana Wickramage",
    "Music": " රූකන්ත ගුනතිලක",
    "song_lyrics": "      \n     \nළඟින් මගේ ඔබ සතපා හදින් මගේ කතා කළා\nහදට ඔබේ නොදැණුනාද\nමගේ ආදරේ මගේ ආදරේ                    \n    \t\t\t\t\nඇවිත් වගේ අඳුරු වලා ඔබ ළඟ නෑ දුරස් වෙලා\nපෙම් කළ හද වෙනස් වෙලා මක් උනාද මේ\nනැතුව ආදරේ ඔබේ ආදරේ\n  \t\t\t\t\nමගේ හදින් දුරස් වන්න අන් හදකට පෙම් කරන්න\nහදට ඔබේ හැකි උනාද නැතුව ආදරේ\nමගේ ආදරේ මගේ ආදරේ\nඅඳුරු වලාකුළක් වගේ අඳුරුයි දැන් සිතද මගේ\nමගේ කඳුළු පිසලන්නටනොහැකි වේද ඔබේ සිතට\nපුදා ආදරේ මගේ ආදරේ\nඅළුත් පෙමින් විඩා වෙලා ආවෝතින් මාව සොයා\nඅතීතයට සමුදීලා පිළිගන්නට හිඳියි බලා\nමගේ ආදරේ මගේ ආදරේ\n",
    "Artist_si": " චන්ඩ්‍රලෙඛ පෙරෙර",
    "Lyrics_si": " නන්ඩන විcක්‍රමගෙ",
    "searchable_lyric": "Lanngin magei oba satapaa hadin magei kataa kaLaa\nhadaTa obei nodANunaada\nmagei aadarei magei aadarei                    \n    \t\t\t\t\nAwit wagei anndhuru walaa oba Lannga nAa duras welaa\npem kaLa hada wenas welaa mak unaada mei\nnAtuwa aadarei obei aadarei\n  \t\t\t\t\nmagei hadin duras wanna an hadakaTa pem karanna\nhadaTa obei hAki unaada nAtuwa aadarei\nmagei aadarei magei aadarei\nanndhuru walaakuLak wagei anndhuruyi dAn sitada magei\nmagei kanndhuLu pisalannaTanohAki weida obei sitaTa\npudaa aadarei magei aadarei\naLut pemin wiDaa welaa aawoetin maawa soyaa\natietayaTa samudielaa piLigannaTa hinndhiyi balaa\nmagei aadarei magei aadarei"
}