{
    "title": "Atheethye pawa – අතීතයේ පවා",
    "views": 409,
    "Genre": " Old Pops",
    "Artist": " Milton Mallawarachchi",
    "Lyrics": " K.D.K.Dharmawardhana",
    "Music": " ස්ටන්ලෙය් පීරිස්",
    "song_lyrics": "    \t                  \nඅතීතයේ පවා  මගේ ලඟින් සිටී\nභවෙන් භවේ පැතූ මා\nඔබේය සෑමදා\nදවසක මා……අමතා…නොපෙනී……කතා කලා\nදිනකදි මා…හඬවා…මා පෙලා……නිහඬ වුනා\nකෙදිනක හෝ…ඔබගේ…නොයිඳුල්… සෙනෙහෙ විලේ\nසිනාසෙන්නම් නැවතී ආදරෙන් සිතූ ලෙසින්\n",
    "Artist_si": " මිල්ටොන් මල්ලවරච්චි",
    "Lyrics_si": " ක්.ඩ්.ක්.දර්මවර්දන",
    "searchable_lyric": "atietayei pawaa  magei lanngin siTie\nbhawen bhawei pAtuu maa\nobeiya sAamadaa\ndawasaka maa……amataa…nopenie……kataa kalaa\ndinakadi maa…hanndawaa…maa pelaa……nihannda wunaa\nkedinaka hoe…obagei…noyinndhul… senehe wilei\nsinaasennam nAwatie aadaren situu lesin"
}