{
    "title": "Kunda Saman – කුන්ද සමන්",
    "views": 711,
    "Genre": " Old Pops",
    "Artist": " T.M.Jayarathna",
    "Lyrics": " Clarence Wijewardena",
    "Music": " cලරෙන්cඑ විජෙවර්ඩෙන",
    "song_lyrics": "කුන්ද සමන් මල් මල් රැන්දු සිනාවා \nකන්ද උඩින් පෑයූ චන්ද්‍ර සිනාවා \n\t                 \nනෙල්ලි කැලේ හැංගී ඉන්න කුමාරී \n\t               \nපින්න පිපුනු සීතේ එන්න සිනාසී \nරංචු බිඟුන් සේනා    කැන්දු සිනාවා \nපුංචි සමන් මල් රොන් බිංදු සිනාවා\n   \t\t             \nපිපි මලසේහිමිදිරියේඔසරි පොටේ\n        \t      \nසුදු නෙරියේහිත දැවටේසිලි සිලියේ\n   \t\t             \nමට නොදැනීමට අමතාපටු නළලේ \n       \t   \nකියඹු ලතාමුදු මුදුසේසැලෙන ලතා \n",
    "Artist_si": " ට්.ම්.ජයරත්න",
    "Lyrics_si": " cලරෙන්cඑ විජෙවර්ඩෙන",
    "searchable_lyric": "kunda saman mal mal rAndu sinaawaa \nkanda uDin pAayuu candra sinaawaa \n\t                 \nnelli kAlei hA\\ngie inna kumaarie \n\t               \npinna pipunu sietei enna sinaasie \nra\\ncu binngun seinaa    kAndu sinaawaa \npu\\nci saman mal ron bi\\ndu sinaawaa\n   \t\t             \npipi malaseihimidiriyeiosari poTei\n        \t      \nsudu neriyeihita dAwaTeisili siliyei\n   \t\t             \nmaTa nodAniemaTa amataapaTu naLalei \n       \t   \nkiyaBu lataamudu muduseisAlena lataa"
}