{
    "title": "Landune Landune – ළඳුනේ",
    "views": 3058,
    "Genre": " Classics",
    "Artist": " Amarasiri Peiris",
    "Lyrics": " Ranbanda Senevirathna",
    "Music": " ප්‍රෙමසිරි ඛෙමඩස",
    "song_lyrics": " —  —  — \n  —  — \n — \nළඳුනේ ළඳුනේ… \n —  —  — \n  —  — \n — \nඔබේ දෑස දැකගත්තෙමි \nසැඳෑ කලෙක ළඳුනේ  ළඳුනේ\nදෙනෝ දහක් අත ගත්තද \nසැමියෙකු නැති ළඳුනේ \n\t\t\t\t     \nනෑයෙක් නෑකම නොකියන \nවීදි සරණ ළඳුනේ    \nතෙල් මල් ගෙන දෝත පුරා\nමුනිකුටියට පියමං වන\nඔබේ දෑස දැක ගත්තෙමි \nසැඳෑ කලෙක ළඳුනේ  ළඳුනේ \n —  —  \n  —  — \nබුදුන් දැක නිවන් දකිමැයි \nදෙව්රම යන පාර අහන\nඔබ ද පටාචාරාවකී \nඔබ ද කිසාගෝතමියකි\n   —  — \nපිරිමින්ගෙ පාප කඳට දෝස විඳින ළඳුනේ\nඅඳුරේ පව් කරන දනා එළියෙ රවන ළඳුනේ\nළැම පමණක් ලොවට පෙනෙන \nළය නොපෙනෙන ළඳුනේ\nකුහුඹුවකුට වරදක් නැති වැරදිකාර ළඳුනේ\n",
    "Artist_si": " අමරසිරි පේරිස්",
    "Lyrics_si": " රන්බන්ඩ සෙනෙවිරත්න",
    "searchable_lyric": "—  —  — \n  —  — \n — \nLanndhunei Lanndhunei… \n —  —  — \n  —  — \n — \nobei dAasa dAkagattemi \nsAnndhAa kaleka Lanndhunei  Lanndhunei\ndenoe dahak ata gattada \nsAmiyeku nAti Lanndhunei \n\t\t\t\t     \nnAayek nAakama nokiyana \nwiedi saraNa Lanndhunei    \ntel mal gena doeta puraa\nmunikuTiyaTa piyama\\n wana\nobei dAasa dAka gattemi \nsAnndhAa kaleka Lanndhunei  Lanndhunei \n —  —  \n  —  — \nbudun dAka niwan dakimAyi \ndewrama yana paara ahana\noba da paTaacaaraawakie \noba da kisaagoetamiyaki\n   —  — \npiriminge paapa kanndhaTa doesa winndhina Lanndhunei\nanndhurei paw karana danaa eLiye rawana Lanndhunei\nLAma pamaNak lowaTa penena \nLaya nopenena Lanndhunei\nkuhuBuwakuTa waradak nAti wAradikaara Lanndhunei"
}