{
    "guitar_key": "G Major",
    "beat": "2/4",
    "title": "Eka Warak Obata – එක වරක් ඔබට",
    "views": 633,
    "Genre": " Old Pops",
    "Artist": " Vijaya Kumarathunga",
    "Lyrics": " Sunil Ariyarathna",
    "Music": " සරත් ඩසනයක",
    "song_lyrics": "එක වරක් ඔබට මා එපා නම්\nසිය දහස් වාරයක් එපා මට ඔබ එපා\nමම මගේ පාඩුවේ හඬ හඬා සිටින්නම්\nඔබ ඔබේ ලෝකයේ මිණි කිරුල පළඳින්න\nඔබේ හද පහුරුගා වේදනා නොදෙන්නම්\nඔබ යනෙන මාවතේ දැක ගන්න ඉඩ දෙන්න\n",
    "Artist_si": " විජය කුමරතුන්ග",
    "Lyrics_si": " සුනිල් අරියරත්න",
    "searchable_lyric": "eka warak obaTa maa epaa nam\nsiya dahas waarayak epaa maTa oba epaa\nmama magei paaDuwei hannda hanndaa siTinnam\noba obei loekayei miNi kirula paLanndhinna\nobei hada pahurugaa weidanaa nodennam\noba yanena maawatei dAka ganna iDa denna"
}