{
    "guitar_key": "A minor",
    "beat": "4/4",
    "title": "Mal Pipila – මල් පිපිලා ",
    "views": 1052,
    "Genre": " Old Pops",
    "Artist": " Dayarathna Ranathunga",
    "Lyrics": " Chandrasena Range",
    "Music": " ස්ටන්ලෙය් ම් ෆෙර්නන්ඩො",
    "song_lyrics": "මල් පිපිලා \nමල් පිපිලා ජීවිත උයනේ මල් පිපිලා \nආත්මයේ දසන්තයේ සුවඳ ගලා \nප්‍රාර්ථනා මල් පිපිලා මල් පිපිලා\nමගෙ දෙතොලට ඔබෙ දෙකොපුල හිමි නැත \nමගෙ දෑතට ඔබෙ රතැඟිලි හිමි නැත \nඑත් මගේ යුග දෙනෙතට උරුමයි \nකම් නැත මියුලැසියේ \nඒ ඇති මට මගෙ නෙත් යුග පියෙන තුරා\nමල් පිපිලා\nරෑ බඹරෙකු මා දකින වෙලාවක \nමධු පිරි මලකට ඇදෙන වෙලාවක\nආශා රැහැනින් හදවත පිබිදෙයි \nකම් නැත මියුලැසියේ \nසිහින ලොවේදී මා ඔබ දකින තුරා \nමල් පිපිලා\n",
    "Artist_si": " ඩයරත්න රනතුන්ග",
    "Lyrics_si": " චන්ඩ්‍රසෙන රන්ගෙ",
    "searchable_lyric": "mal pipilaa \nmal pipilaa jiewita uyanei mal pipilaa \naatmayei dasantayei suwanndha galaa \npraarthanaa mal pipilaa mal pipilaa\nmage detolaTa obe dekopula himi nAta \nmage dAataTa obe ratAnngili himi nAta \net magei yuga denetaTa urumayi \nkam nAta miyulAsiyei \nea Ati maTa mage net yuga piyena turaa\nmal pipilaa\nrAa baBareku maa dakina welaawaka \nmadhu piri malakaTa Adena welaawaka\naaSaa rAhAnin hadawata pibideyi \nkam nAta miyulAsiyei \nsihina loweidie maa oba dakina turaa \nmal pipilaa"
}