{
    "guitar_key": "Eb major",
    "beat": "4/4",
    "title": "Dakina Dasune –  දකින දසුනේ",
    "views": 1733,
    "Genre": " Movie Songs",
    "Artist": " H.R.Jothipala",
    "Lyrics": " Karunarathna Abeysekara",
    "Music": " ට් ෆ් ලටිෆ්",
    "song_lyrics": "\t\t\t    \n\t\t\t\t\t\t\t\t\nදකින දසුනේ දෙනෙත ඇඳුනේ \nසොඳුරු ඔබෙ රුව වේ\n               \t\t\t      \nපවනෙ ඇසුනේ සවන රැඳුනේ \nඔබගෙ කට හඬ වේ\n\t\t \nඔබගෙ කට හඬ වේ\n\t\t\t    \nමහද විමනේ කැකුළු යහනේ \nඔබයි සැතපෙන්නේ\n                \t\t\t\t    \nසිතන සිතුමේ පතන පැතුමේ \nඔබයි හිනැහෙන්නේ\n\t       \nඔබයි හිනැහෙන්නේ \nදෙපස ගංගා දෙකකි එක්වී \nඑක තැනට ආවේ\n                \t\t\t\t    \nඑකම ඒ ගං ජලය මුසුවී \nසයුර තුළ පාවේ\n\t    \nසයුර තුළ පාවේ\n",
    "Artist_si": " හ්.ර්.ජොතිපල",
    "Lyrics_si": " කරුනරත්න අබෙය්සෙකර",
    "searchable_lyric": "dakina dasunei deneta Anndhunei \nsonndhuru obe ruwa wei\n               \t\t\t      \npawane Asunei sawana rAnndhunei \nobage kaTa hannda wei\n\t\t \nobage kaTa hannda wei\n\t\t\t    \nmahada wimanei kAkuLu yahanei \nobayi sAtapennei\n                \t\t\t\t    \nsitana situmei patana pAtumei \nobayi hinAhennei\n\t       \nobayi hinAhennei \ndepasa ga\\ngaa dekaki ekwie \neka tAnaTa aawei\n                \t\t\t\t    \nekama ea ga\\n jalaya musuwie \nsayura tuLa paawei\n\t    \nsayura tuLa paawei"
}