{
    "guitar_key": "F major",
    "beat": "4/4",
    "title": "Dura Atha Jeewithe – දුර ඈත ජීවිතේ",
    "views": 950,
    "Genre": [
        " Old Pops",
        " Request"
    ],
    "Artist": " Lakshman Wijesekara",
    "Lyrics": " Kularathna Ariyawansa",
    "Music": " ලක්ශ්මන් විජෙසෙකර",
    "song_lyrics": "දුර ඈත ජීවිතේ  පිපිසේ අවාරයේ\nඒ ආදරේ සෙනේ වේදනා මාරුතේ\nදෑසේ වෙලී ඔබේ ආරාධනා මැවේ\nදෑසේ වෙලී ඔබේ ආරාධනා මැවේ\nමසිතේ ගලා හැලේ සිහිනේ අතීතයේ\nමා ඒ අතීතයේ ඈ හා මුලා  වෙලා \nමා ඒ අතීතයේ ඈ හා මුලා  වෙලා\nපිදු ඒ ස්නේහයේ සිත මා බැඳී ගියේ\nදුර ඈත ජීවිතේ  පිපිසේ අවාරයේ\nඒ ආදරේ සෙනේ වේදනා මාරුතේ\nදුර ඈත ජීවිතේ\n",
    "Artist_si": " ලක්ශ්මන් විජෙසෙකර",
    "Lyrics_si": " කුලරත්න අරියවන්ස",
    "searchable_lyric": "dura Aata jiewitei  pipisei awaarayei\nea aadarei senei weidanaa maarutei\ndAasei welie obei aaraadhanaa mAwei\ndAasei welie obei aaraadhanaa mAwei\nmasitei galaa hAlei sihinei atietayei\nmaa ea atietayei Aa haa mulaa  welaa \nmaa ea atietayei Aa haa mulaa  welaa\npidu ea sneihayei sita maa bAnndhie giyei\ndura Aata jiewitei  pipisei awaarayei\nea aadarei senei weidanaa maarutei\ndura Aata jiewitei"
}