{
    "guitar_key": "C Major",
    "beat": "3/4",
    "title": "Ma Ekkala – මා එක්කලා",
    "views": 2683,
    "Genre": " Classics",
    "Artist": " Malani Bulathsinhala",
    "Lyrics": " Premakeerthi De Alwis",
    "Music": " ඖස්ටින් මුනසින්ඝෙ",
    "song_lyrics": "මා එක්කලා අමනාප ව වී දබර\n දූ ගේ තාත්තා එන්නේ නැහැ ගෙදර\nවැලි පොල්කටුයි හැඳි රෑනයි පෙරලා ලා\n                               \nමිදුලේ වැටුණු කොළ සේරම අතුගාලා\n                            \nගේ ළඟ වැට කඩුල්ලට බැරි බර දීලා\n                           \nරෑ එළිවෙන තුරා ඉමු මිදුළට වී ලා\nහඳ මාමා නැඟෙන තුරු අපි තරු ගනිමූ \nදෙදෙනාගේ ම දුක තල් අත්තක ලියමූ \nහඳ මාමා අත ම ඒ පණිවුඩ යවමූ \nහෙටවත් ගෙදර ඒ දැයි බලමින් හිඳිමූ\n",
    "Artist_si": " මලනි බුලත්සින්හල",
    "Lyrics_si": " ප්‍රෙමකීර්ති ඩෙ අල්විස්",
    "searchable_lyric": "maa ekkalaa amanaapa wa wie dabara\n duu gei taattaa ennei nAhA gedara\nwAli polkaTuyi hAnndhi rAanayi peralaa laa\n                               \nmidulei wATuNu koLa seirama atugaalaa\n                            \ngei Lannga wATa kaDullaTa bAri bara dielaa\n                           \nrAa eLiwena turaa imu miduLaTa wie laa\nhanndha maamaa nAnngena turu api taru ganimuu \ndedenaagei ma duka tal attaka liyamuu \nhanndha maamaa ata ma ea paNiwuDa yawamuu \nheTawat gedara ea dAyi balamin hinndhimuu"
}